springcloudstream/__init__.py
springcloudstream/component.py
springcloudstream/encoders.py
springcloudstream/options.py
springcloudstream/portability.py
springcloudstream/grpc/__init__.py
springcloudstream/grpc/message.py
springcloudstream/grpc/messagehandler.py
springcloudstream/grpc/stream.py
springcloudstream/proto/__init__.py
springcloudstream/proto/message_pb2.py
springcloudstream/proto/processor_pb2.py
springcloudstream/proto/processor_pb2_grpc.py
springcloudstream/stdio/__init__.py
springcloudstream/stdio/messagehandler.py
springcloudstream/stdio/stream.py
springcloudstream/tcp/__init__.py
springcloudstream/tcp/messagehandler.py
springcloudstream/tcp/stream.py
springcloudstream/tcp/tcp.py
springcloudstream-1.1.6.dist-info/DESCRIPTION.rst
springcloudstream-1.1.6.dist-info/METADATA
springcloudstream-1.1.6.dist-info/RECORD
springcloudstream-1.1.6.dist-info/WHEEL
springcloudstream-1.1.6.dist-info/metadata.json
springcloudstream-1.1.6.dist-info/top_level.txt
