Metadata-Version: 2.0
Name: springcloudstream
Version: 1.1.6
Summary: A package to support invocation of remote Python applications via Spring Cloud Stream
Home-page: https://github.com/dturanski/springcloudstream
Author: David Turanski
Author-email: dturanski@pivotal.io
License: Apache Software License (http://www.apache.org/licenses/LICENSE-2.0)
Platform: UNKNOWN
Classifier: Development Status :: 4 - Beta
Classifier: Intended Audience :: Developers
Classifier: Topic :: Software Development :: Libraries :: Python Modules
Classifier: License :: OSI Approved :: Apache Software License
Classifier: Programming Language :: Python :: 2
Classifier: Programming Language :: Python :: 2.7
Classifier: Programming Language :: Python :: 3
Classifier: Programming Language :: Python :: 3.4
Classifier: Programming Language :: Python :: 3.5
Classifier: Programming Language :: Python :: 3.6
Requires-Dist: grpcio
